<?xml version="1.0" encoding="UTF-8" ?>

<!DOCTYPE node PUBLIC
  "-//freedesktop//DTD D-Bus Object Introspection 1.0//EN"
  "http://standards.freedesktop.org/dbus/1.0/introspect.dtd">

<node>
  <interface name="org.tizen.telephony.Modem">

    <!-- Refer to TAPI API: tapi_modem_set_power_status() -->
    <method name="SetPowerStatus">
      <arg direction="in" type="i" name="status"/>
      <arg direction="out" type="i" name="result"/>
    </method>

    <!-- Refer to TAPI API: tapi_modem_set_flight_mode() -->
    <method name="SetFlightMode">
      <arg direction="in" type="b" name="enable"/>
      <arg direction="out" type="i" name="result"/>
    </method>

    <!-- Refer to TAPI API: tapi_modem_get_flight_mode() -->
    <method name="GetFlightMode">
      <arg direction="out" type="i" name="result"/>
      <arg direction="out" type="b" name="enable"/>
    </method>

    <!-- Refer to TAPI API: tapi_modem_get_version() -->
      <method name="GetVersion">
      <arg direction="out" type="i" name="result"/>
      <arg direction="out" type="s" name="software_version"/>
      <arg direction="out" type="s" name="hardware_version"/>
      <arg direction="out" type="s" name="calibration_date"/>
      <arg direction="out" type="s" name="product_code"/>
    </method>

    <!-- Refer to TAPI API: tapi_modem_get_imei() -->
    <method name="GetImei">
      <arg direction="out" type="i" name="result"/>
      <arg direction="out" type="s" name="imei"/>
    </method>

    <!-- Caches power status -->
    <property name="status" type="i" access="read"/>

    <!-- Caches flight mode status -->
    <property name="flight_mode_status" type="i" access="read"/>

    <!-- Caches IMEI value -->
    <property name="imei" type="s" access="read"/>

    <!--
         Version information
         @version: software_version, hardware_version, calibration_date, product_code
    -->
    <property name="version" type="a{sv}" access="read"/>

  </interface>
</node>
